eventdetector_ts/__init__.py
eventdetector_ts/data/__init__.py
eventdetector_ts/data/helpers_data.py
eventdetector_ts/data/interval.py
eventdetector_ts/metamodel/__init__.py
eventdetector_ts/metamodel/meta_model.py
eventdetector_ts/metamodel/utils.py
eventdetector_ts/models/__init__.py
eventdetector_ts/models/helpers_models.py
eventdetector_ts/models/models_builder.py
eventdetector_ts/models/models_trainer.py
eventdetector_ts/optimization/__init__.py
eventdetector_ts/optimization/algorithms.py
eventdetector_ts/optimization/event_extraction_pipeline.py
eventdetector_ts/plotter/__init__.py
eventdetector_ts/plotter/helpers.py
eventdetector_ts/plotter/plotter.py
eventdetector_ts/prediction/__init__.py
eventdetector_ts/prediction/prediction.py
eventdetector_ts/prediction/utils.py
eventdetector_ts-1.1.0.dist-info/LICENSE
eventdetector_ts-1.1.0.dist-info/WHEEL
eventdetector_ts-1.1.0.dist-info/METADATA
eventdetector_ts-1.1.0.dist-info/RECORD
