Metadata-Version: 2.1
Name: eventdetector_ts
Version: 1.1.0
Summary: EventDetector introduces a universal event detection method for multivariate time series. Unlike traditional deep-learning methods, it's regression-based, requiring only reference events. The robust stacked ensemble, from Feed-Forward Neural Networks to Transformers, ensures accuracy by mitigating biases. The package supports practical implementation, excelling in detecting events with precision, validated across diverse domains.
Keywords: Universal Event Detection,Multivariate Time Series,Regression-based,Stacked Ensemble Learning,Deep Learning Models,Feed-Forward Neural Networks,Transformers,Event Detection Package,Rare Events,Imbalanced Datasets,Anomaly Detection,Change Point Detection,Fraud Detection,Empirical Validations
Author-email: Menouar Azib <menouar.azib@akkodis.com>
Maintainer-email: Menouar Azib <menouar.azib@akkodis.com>
Requires-Python: >=3.9
Classifier: License :: OSI Approved :: MIT License
Classifier: Programming Language :: Python :: 3
Classifier: Operating System :: OS Independent
Requires-Dist: joblib
Requires-Dist: matplotlib
Requires-Dist: numpy
Requires-Dist: pandas
Requires-Dist: python_dateutil
Requires-Dist: scikit_learn
Requires-Dist: scipy
Requires-Dist: seaborn
Requires-Dist: sympy
Requires-Dist: colorlog
Requires-Dist: pydot
Requires-Dist: pyqt5
Requires-Dist: tqdm
Project-URL: Bug Tracker, https://github.com/menouarazib/eventdetector/issues
Project-URL: Homepage, https://github.com/menouarazib/eventdetector
